{
  "schemaVersion": 1,
  "id": "onesuperblock",
  "version": "${version}",
  "name": "OneSuperBlock Mod",
  "description": "OneSuperBlock",
  "authors": [
    "Takacick"
  ],
  "contact": {
    "homepage": "https://fabricmc.net/",
    "sources": "https://github.com/FabricMC/fabric-example-mod"
  },
  "license": "CC0-1.0",
  "icon": "assets/onesuperblock/icon.png",
  "environment": "*",
  "accessWidener": "onesuperblock.accesswidener",
  "entrypoints": {
    "main": [
      "de.takacick.onesuperblock.OneSuperBlock"
    ],
    "client": [
      "de.takacick.onesuperblock.OneSuperBlockClient"
    ]
  },
  "mixins": [
    "onesuperblock.mixins.json"
  ],
  "depends": {
    "bionicutils": ">=1.1.2",
    "superitems": ">=1.0.0",
    "fabricloader": ">=0.14.6",
    "fabric": "*",
    "minecraft": "~1.19",
    "java": ">=17"
  },
  "suggests": {
    "another-mod": "*"
  }
}
